{
  "text_sample": "FRANCHISE DISCLOSURE DOCUMENT 1 TOM PLUMBER GLOBAL INC. (an Ohio corporation) 24 Whitney Drive, Suite B Milford, OH 45150 1 -855 -832 -6866 angie@1tomplumber.com www.1tomplumber.com 1 Tom Plumber Global Inc. offers franchises to operate a 1-Tom-Plumber\u00ae plumbing business focused on emergency plumbing services and repairs at commercial and residential properties. The total investment necessary to begin operation of a 1 Tom Plumber franchise ranges from $515,719 t to $ $2,784,795 . This includes $50,000 that must be paid to the franchisor as an initial franchise fee. This Disclosure Document summarizes certain provisions of your franchise agreement and other information in plain English. Read this Disclosure Document and all accompanying agreements carefully. You must receive this Disclosure Document at least 14 calendar -days before you sign a binding agreement with, or make any payment to, us or an affiliate in connection with the proposed franchise sale. Note, however, that no governm",
  "extracted_info": {
    "address": {
      "city": "Milford",
      "state": "OH",
      "street": "24 Whitney Drive, Suite B",
      "zip": "45150"
    },
    "business_description": "1 Tom Plumber Global Inc. offers franchises to operate a 1-Tom-Plumber\u00ae plumbing business focused on emergency plumbing services and repairs at commercial and residential properties.",
    "fdd_year": 2024,
    "franchise_name": "1 Tom Plumber Global Inc.",
    "issuance_date": "April 1, 2024",
    "contact_info": {
      "email": "angie@1tomplumber.com",
      "phone": "1-855-832-6866",
      "website": "www.1tomplumber.com"
    },
    "franchise_system_description": "The franchise operates a drain cleaning and full-service plumbing business focused on emergency services and repairs for commercial and residential properties using the franchisor's methods of operation, trademarks, and other branded materials.",
    "incorporation_date": "January 27, 2020",
    "initial_franchise_fee": "$50,000",
    "legal_entity_type": "Ohio corporation",
    "principal_business_address": "24 Whitney Drive, Suite B, Milford, Ohio 45150",
    "state_of_incorporation": "Ohio",
    "total_investment_range": {
      "max": "$2,784,795",
      "min": "$515,719"
    }
  }
}